[{"user": {"id": 1737831474802679808, "id_str": "1737831474802679808", "name": "Pam Willson", "screen_name": "PamWillson47105"}, "next_link": {"link_type": "subtask", "link_id": "next_link", "subtask_id": "SuccessExit"}, "oauth_token": "1737831474802679808-fdk8Q0E4PGH0jFtILGJLRugC2EBWC5", "oauth_token_secret": "DDlUKSFDSen2B6mizynbqJwNbiVNhxUwNoxbTU184mSeG", "known_device_token": "wSUaGQyCBI48xNWLJ2EhH3a6XOm8Qob543xStKZk", "attribution_event": "login"},
{"user": {"id": 1737925626768576512, "id_str": "1737925626768576512", "name": "Claudia Saylor", "screen_name": "ClaudiaSay90855"}, "next_link": {"link_type": "subtask", "link_id": "next_link", "subtask_id": "SuccessExit"}, "oauth_token": "1737925626768576512-Dadrl3BB8K3WlDs6ydxOiKCN9gy33H", "oauth_token_secret": "eBd56S7Xp2TJMX2POiloYHnd69ASp8m3WulEwuWdiZwGb", "known_device_token": "zS6GNm8EdcnOamIn1cx7LGOurx1f1GMl5gzuevjf", "attribution_event": "login"},
{"user": {"id": 1737831201392697345, "id_str": "1737831201392697345", "name": "Cassandra Morrison", "screen_name": "CassandraM27025"}, "next_link": {"link_type": "subtask", "link_id": "next_link", "subtask_id": "SuccessExit"}, "oauth_token": "1737831201392697345-BRMG9zfm4ZtQE7mce8Ogk9qlqva88H", "oauth_token_secret": "tCrWj5buJTWPSXZbH6qDR5OqlXiygoS12dWhmjCNdzMeo", "known_device_token": "3LnATyoKGK4EzVPld9O2qvBRYRNm0tC0zMOVjUd5", "attribution_event": "login"},
{"user": {"id": 1737830930465935360, "id_str": "1737830930465935360", "name": "Katie Hopkinson", "screen_name": "KatieHopki13047"}, "next_link": {"link_type": "subtask", "link_id": "next_link", "subtask_id": "SuccessExit"}, "oauth_token": "1737830930465935360-lTsI3ApBJK9lHg5UIFSqrvPrWYigII", "oauth_token_secret": "x81CP2VtpY8isML2NTtrVEqGZwiahDqpmd9SHKIfy0Gsw", "known_device_token": "am1PAc2a8CAu6bzfb50ic1KVPRJhwbjyGnHT3WK8", "attribution_event": "login"},
{"user": {"id": 1737831611755069440, "id_str": "1737831611755069440", "name": "Andrea Roberts", "screen_name": "AndreaRobe37395"}, "next_link": {"link_type": "subtask", "link_id": "next_link", "subtask_id": "SuccessExit"}, "oauth_token": "1737831611755069440-AHVAnbysvs05QubLCu4BuluFND1Fqm", "oauth_token_secret": "vOYs0HwwuDokrHCJ7e9dnPoxtvjXuCfPcQ2Jzf1PHHxbD", "known_device_token": "aUUAfU3X9NyzEVadX6dazCKZR2t9ROy6Uxv6CTIE", "attribution_event": "login"},
{"user": {"id": 1737831524538712064, "id_str": "1737831524538712064", "name": "Monique Williams", "screen_name": "MoniqueWil51701"}, "next_link": {"link_type": "subtask", "link_id": "next_link", "subtask_id": "SuccessExit"}, "oauth_token": "1737831524538712064-RoPvXiuIbRKysmf3orUk677aV1VJdi", "oauth_token_secret": "hxEcLy7g8KUNEXYNjsRiJfOb3AjR913sgkwupuqGTeY06", "known_device_token": "t5Q0UmiGkC8VoCo6InTnEWKAtS4c1WsGm8l4B7x3", "attribution_event": "login"},
{"user": {"id": 1737831536215695360, "id_str": "1737831536215695360", "name": "Katie Madore", "screen_name": "KatieMador24356"}, "next_link": {"link_type": "subtask", "link_id": "next_link", "subtask_id": "SuccessExit"}, "oauth_token": "1737831536215695360-sgSFbZsXvuxO60KtunyTWd20PE1m6g", "oauth_token_secret": "7Z5znJbt3aSydEVPK5GXs4QLeZUYTL2QxoCzUAPeRO1qP", "known_device_token": "48pl8z2PeahFbkSRSp6xL1iPByg8Jx4QICCMG9J6", "attribution_event": "login"},
{"user": {"id": 1737831529173454849, "id_str": "1737831529173454849", "name": "Maria Benitez", "screen_name": "MariaBe5829426"}, "next_link": {"link_type": "subtask", "link_id": "next_link", "subtask_id": "SuccessExit"}, "oauth_token": "1737831529173454849-hw8UVkkbf50b00nsaJzMHtxyqZnhlB", "oauth_token_secret": "yptT1A9lqfMoWDTTyPqjS7VHKhK9AEKaAMr1DFYXGvYUZ", "known_device_token": "f6FzQ9zuXflmdTkHii2D8gYiPa15nkw9hFmBSZYt", "attribution_event": "login"},
{"user": {"id": 1737830375471390720, "id_str": "1737830375471390720", "name": "Kathy Love", "screen_name": "KathyLo60993817"}, "next_link": {"link_type": "subtask", "link_id": "next_link", "subtask_id": "SuccessExit"}, "oauth_token": "1737830375471390720-tqXQQ2ynpbtiRw1aULWipOL9gliku5", "oauth_token_secret": "dpIa74gzlzp59BHqSr4pQI5EqW2kzzTbdrBVn2i88J1Fp", "known_device_token": "ScHT25gERdBz81ubAb7nXeM5ATAbhRzBNzZ3EUTZ", "attribution_event": "login"},
{"user": {"id": 1737829375830319104, "id_str": "1737829375830319104", "name": "Sandy Hansen", "screen_name": "SandyHanse37606"}, "next_link": {"link_type": "subtask", "link_id": "next_link", "subtask_id": "SuccessExit"}, "oauth_token": "1737829375830319104-K0VS0SNyUJumOp4JyNC4MswmYuDY0P", "oauth_token_secret": "mzyjXQKSt84fpki71rSkAo6cxkwU3RnQty2qfUtyhP34g", "known_device_token": "gAMrPgTmA3u3wYQkdrxOhnjQTDUfgW5hGLz3MOgB", "attribution_event": "login"},
{"user": {"id": 1737830612978065408, "id_str": "1737830612978065408", "name": "Donna Marshall", "screen_name": "DonnaMarsh59758"}, "next_link": {"link_type": "subtask", "link_id": "next_link", "subtask_id": "SuccessExit"}, "oauth_token": "1737830612978065408-szdzBZWD1kMH9VCqSWJ7K7WDDv3DPW", "oauth_token_secret": "J7l1n68nGPnjW4WLmv57iAXu3GMEOkz24UxCFGqCOvfKY", "known_device_token": "MuoP7FvpBHsLKpmTDUYBWT30fa16gOO3tJngTfAl", "attribution_event": "login"},
{"user": {"id": 1737830021237276672, "id_str": "1737830021237276672", "name": "Angela Hawkins", "screen_name": "AngelaHawk80567"}, "next_link": {"link_type": "subtask", "link_id": "next_link", "subtask_id": "SuccessExit"}, "oauth_token": "1737830021237276672-fi9DFYl8PZX8XuZOhbpiv28NpCgcxO", "oauth_token_secret": "mBNAgFeHcNZVcIDlpgjBGVTQH9vbQCYAhxS9OGe2PsbiB", "known_device_token": "qnQtQRbCBjpj1EFYwM5fYPuADDbGb8sWCxj0atOS", "attribution_event": "login"},
{"user": {"id": 1737830896617807872, "id_str": "1737830896617807872", "name": "Sohini Pittinato", "screen_name": "pittinato1635"}, "next_link": {"link_type": "subtask", "link_id": "next_link", "subtask_id": "SuccessExit"}, "oauth_token": "1737830896617807872-KPl04iwwUszQ8LeAqknlipGRMzwT4d", "oauth_token_secret": "9rUpKBD89w6fNCwKklqXBp4yrzlH6fEovKf9odqxSOKbU", "known_device_token": "c6st1eaOQwdXD1FBdG3o080ENlTLJesSFdDOmJO6", "attribution_event": "login"},
{"user": {"id": 1737829983165591552, "id_str": "1737829983165591552", "name": "Sara Varela", "screen_name": "SVarela27734"}, "next_link": {"link_type": "subtask", "link_id": "next_link", "subtask_id": "SuccessExit"}, "oauth_token": "1737829983165591552-3kE99ofbZujA64q4Y320kciOJivXfM", "oauth_token_secret": "dRxKvBwKogwQB0r1Km6FdExiAJZW6pauT1kIumHIqLFWp", "known_device_token": "MobvoNxDJXuRixTTd6hDHWAx6ZRApYKfbsktkOkY", "attribution_event": "login"},
{"user": {"id": 1737829994091675648, "id_str": "1737829994091675648", "name": "Caroline Lee", "screen_name": "CarolineLe73182"}, "next_link": {"link_type": "subtask", "link_id": "next_link", "subtask_id": "SuccessExit"}, "oauth_token": "1737829994091675648-18LfwhwYArXS4QJrmwUozTkuxdVHXF", "oauth_token_secret": "AmFQUwZUeW2cEEbEaNpBQLfn7pHkYzarhbH2VonOeQl1r", "known_device_token": "xU0HSvWYGgit1M383DA7bLZx6lTaQhAOFv5qjYmW", "attribution_event": "login"},
{"user": {"id": 1737829583528095744, "id_str": "1737829583528095744", "name": "Amy Jacobs", "screen_name": "jacobs_amy32429"}, "next_link": {"link_type": "subtask", "link_id": "next_link", "subtask_id": "SuccessExit"}, "oauth_token": "1737829583528095744-isT1aOKUbm4bV3AE4kCHkjPQOAEhL8", "oauth_token_secret": "DCLhSF2mEbM8u5Gj4AjU6MK72cSlRlPAqndScYYFLgm9Y", "known_device_token": "vaRsSjq9TPLjzjB7rO3aqjMQQwlYnoTYk8NYqYGS", "attribution_event": "login"},
{"user": {"id": 1737830968072060928, "id_str": "1737830968072060928", "name": "Ashley Wilson", "screen_name": "AshleyWils55781"}, "next_link": {"link_type": "subtask", "link_id": "next_link", "subtask_id": "SuccessExit"}, "oauth_token": "1737830968072060928-wWRjj5G5V2fJmIbCSbEg8dEFZNA17V", "oauth_token_secret": "P9wGGvZXs2FD9OT0fjG3ngzUpqUEMrCaeoVDnKklYMsGF", "known_device_token": "DJQGTs9U3CCta0bhEHS9ozcwRScsBGE5djJP6eog", "attribution_event": "login"},
{"user": {"id": 1737830954444673024, "id_str": "1737830954444673024", "name": "Karla Slater", "screen_name": "SlaterKarl83830"}, "next_link": {"link_type": "subtask", "link_id": "next_link", "subtask_id": "SuccessExit"}, "oauth_token": "1737830954444673024-Uz6PxSBqUmSlPG9hck3oP5Im3OnDDW", "oauth_token_secret": "BfEyN48Q8OvDY851uV55Gtcb5fVAx0lg2oZDdiGpazKPg", "known_device_token": "PqQobHJ2IAA8NDJwy7nGN7ICiIx89MbpEEgf3BOH", "attribution_event": "login"},
{"user": {"id": 1737831009402662912, "id_str": "1737831009402662912", "name": "Mandy Lewis", "screen_name": "MandyLewis70393"}, "next_link": {"link_type": "subtask", "link_id": "next_link", "subtask_id": "SuccessExit"}, "oauth_token": "1737831009402662912-LP289k8QbCtCpX6U00U4TJvEUydi4L", "oauth_token_secret": "liEgkibrMFRL8Xx1ueEmo7k5gS1WJWue3K3Njqasfd9qs", "known_device_token": "UilafwfLpXenLpF2VmUVCofzQIp8kxyn0crxL8Gb", "attribution_event": "login"},
{"user": {"id": 1737830872748101632, "id_str": "1737830872748101632", "name": "Elizabeth Williams", "screen_name": "ElizabethW6891"}, "next_link": {"link_type": "subtask", "link_id": "next_link", "subtask_id": "SuccessExit"}, "oauth_token": "1737830872748101632-xLxnwq16tlrLNis2kk8VbGylEen66M", "oauth_token_secret": "pQvrAonC4If4GVQsainZ0uVwDLH9dxI8hFLX9G2ESBNtm", "known_device_token": "MMrhjMLPcIr82nq0iwDUgNQtPq5ELFwaaJevkttk", "attribution_event": "login"},
{"user": {"id": 1737925384459403264, "id_str": "1737925384459403264", "name": "Pam Correa", "screen_name": "PamCorrea562411"}, "next_link": {"link_type": "subtask", "link_id": "next_link", "subtask_id": "SuccessExit"}, "oauth_token": "1737925384459403264-8OSaEjWS3068d1fUcOoKKaAanR3OE9", "oauth_token_secret": "M1jHxYDPONlDgnrPXjWb7Sauv8ima8MHQ5kOSZQGHsTyi", "known_device_token": "H7tKL7rtYPonJ1wGNuA64UvQ8voL8F25yIEEMpf0", "attribution_event": "login"},
{"user": {"id": 1737925149385719808, "id_str": "1737925149385719808", "name": "Lacey Phelps", "screen_name": "LaceyPhelp91668"}, "next_link": {"link_type": "subtask", "link_id": "next_link", "subtask_id": "SuccessExit"}, "oauth_token": "1737925149385719808-PCwQmcTKhHVXWGGiJ0aSvOigtAXf7T", "oauth_token_secret": "uQVrs0yVF3QKRlwWBo0KaMZXBEbK55bvIMVCj3vqWyJZg", "known_device_token": "6wULpDH0xPtvE4pEOMyP4Bc7nzC2l7yzi6FCSlGJ", "attribution_event": "login"},
{"user": {"id": 1737925571470872576, "id_str": "1737925571470872576", "name": "Andrea Marshall", "screen_name": "AndreaMars98840"}, "next_link": {"link_type": "subtask", "link_id": "next_link", "subtask_id": "SuccessExit"}, "oauth_token": "1737925571470872576-q1on9Ib8DozgIdJRpOvdPofvTMNj22", "oauth_token_secret": "Uj5ctKEHYROLTu3gbg6VFtSIXADZfwl0wK99pWyJkQxpC", "known_device_token": "1Fs2tCi0JdpD1j6dXSP30vGXowFKgrRk3LZuj7P6", "attribution_event": "login"},
{"user": {"id": 1737925617293885442, "id_str": "1737925617293885442", "name": "Xandy Castle", "screen_name": "CastleXand63830"}, "next_link": {"link_type": "subtask", "link_id": "next_link", "subtask_id": "SuccessExit"}, "oauth_token": "1737925617293885442-dIBLMgoQqeDSrE4E63SHMgRLLandgB", "oauth_token_secret": "Fpwswk1eSa8Jk1KVAg1zKX8gBz2Lri5JMd3GjchBMIMWH", "known_device_token": "NMddc5Yuh84n4Bj0dU0q0X75E9c55zqN1h0cw0ux", "attribution_event": "login"},
{"user": {"id": 1737925478617407488, "id_str": "1737925478617407488", "name": "Maria Leonard", "screen_name": "MariaLeona52079"}, "next_link": {"link_type": "subtask", "link_id": "next_link", "subtask_id": "SuccessExit"}, "oauth_token": "1737925478617407488-iLrtYEBZoJskefmDYu1KqercEjhtZZ", "oauth_token_secret": "zRWIRaAz6KZuGwKE7hxBaEBmFRPxbzbq6shtSpZNM5ycW", "known_device_token": "1DRRGZ8vFI9wYJNEyDTbQyDdFS2TUDluRqm1WLCN", "attribution_event": "login"},
{"user": {"id": 1737925939991052288, "id_str": "1737925939991052288", "name": "Maureen Ouellette", "screen_name": "MaureenOue94300"}, "next_link": {"link_type": "subtask", "link_id": "next_link", "subtask_id": "SuccessExit"}, "oauth_token": "1737925939991052288-hkrMujTjGrN4COcMnRuOhxzTqUsD2U", "oauth_token_secret": "dViDwyhioTaqNRCfNR7qJLXMs1JXqVApfkN971qpksoN3", "known_device_token": "cbupRYFIiJ1042VMpbsutCYVbyAejZJnGNeQjWU3", "attribution_event": "login"},
{"user": {"id": 1737926132270321664, "id_str": "1737926132270321664", "name": "Shelly Brown", "screen_name": "ShellyBrow55248"}, "next_link": {"link_type": "subtask", "link_id": "next_link", "subtask_id": "SuccessExit"}, "oauth_token": "1737926132270321664-jEes9u2zgaNXrrrOuaZMJpoHGZX8MU", "oauth_token_secret": "XHZeyMue9PgxVMa3LzErHm2UYkB3dEDp584NYMJU4zq5r", "known_device_token": "LyICifuQDGOlO4fb5JQp3Xq2jAginq9KUHXrgEoh", "attribution_event": "login"},
{"user": {"id": 1737926213551677440, "id_str": "1737926213551677440", "name": "Amber Hawkins", "screen_name": "AmberHawki10252"}, "next_link": {"link_type": "subtask", "link_id": "next_link", "subtask_id": "SuccessExit"}, "oauth_token": "1737926213551677440-Hlkm1KI6aXdkRrT1qFYtnArUMxwn48", "oauth_token_secret": "l9oFVH8Kw4pmu0PhErnh04uVo9SLGHy2JzaqIg3jQ8jXP", "known_device_token": "eVAS9eomdreGwQKsSbTsD7YCBBvQQOXxWAHrb6sd", "attribution_event": "login"},
{"user": {"id": 1737925932696883200, "id_str": "1737925932696883200", "name": "Jennifer Goodnight", "screen_name": "JenniferGo87640"}, "next_link": {"link_type": "subtask", "link_id": "next_link", "subtask_id": "SuccessExit"}, "oauth_token": "1737925932696883200-KRoeqxP2D1o6HumqIlCwHpZtttdjUp", "oauth_token_secret": "zlJmT6FsAoqCiYc1l1s4sejMnhqHQYCznFJhbDaNznh7S", "known_device_token": "ZLMhT7OY0c4TopwGXnKFFwnR7Xwoh8tnvGAPNsPd", "attribution_event": "login"},
{"user": {"id": 1737925350217383937, "id_str": "1737925350217383937", "name": "Sonya Robertson", "screen_name": "SonyaRober62384"}, "next_link": {"link_type": "subtask", "link_id": "next_link", "subtask_id": "SuccessExit"}, "oauth_token": "1737925350217383937-DC24kh4kl7FYLhuTZfjEXYa4Shvgax", "oauth_token_secret": "79DgilHUW5UntgCY96Ka9fwuPpLAgIM9FlEeqKUq7wVIJ", "known_device_token": "sOGlwiHIVXMXftJrVk489wtd0PCmasE2tBsYCyZU", "attribution_event": "login"},
{"user": {"id": 1737925173129674752, "id_str": "1737925173129674752", "name": "Mary Gonia", "screen_name": "GoniaMary54401"}, "next_link": {"link_type": "subtask", "link_id": "next_link", "subtask_id": "SuccessExit"}, "oauth_token": "1737925173129674752-aUb469EeN8v2m3O8klJj1xXlglWYem", "oauth_token_secret": "zVVlo36xvc54WNqsyKBOWj7jpjPyG2pjaQUrjezeZCelD", "known_device_token": "tCedDFMoDw2odGYjpTgjUI7JJxGNt5k29M62c8WK", "attribution_event": "login"},
{"user": {"id": 1737924776113635329, "id_str": "1737924776113635329", "name": "Martha Nerds", "screen_name": "MarthaNerd46582"}, "next_link": {"link_type": "subtask", "link_id": "next_link", "subtask_id": "SuccessExit"}, "oauth_token": "1737924776113635329-jJAcPFAto2R0H5Rcro8DzGbZEEeci1", "oauth_token_secret": "I2SN7zxkdDfFe8MviKdNXZrE5RV8g6fH2PmMENTPXYuNG", "known_device_token": "tUpduHszlwdfReWP9TdPUo5gpRp79YL5xaL2KZJh", "attribution_event": "login"},
{"user": {"id": 1737925509827198977, "id_str": "1737925509827198977", "name": "Kimberly Morales", "screen_name": "KimberlyMo15891"}, "next_link": {"link_type": "subtask", "link_id": "next_link", "subtask_id": "SuccessExit"}, "oauth_token": "1737925509827198977-bmkPREZ70JVTWrl4BJzVzCQHZieM4I", "oauth_token_secret": "rLT0wUHkrr2b1PFfV6yCea0zmh2qiHfMve2KnUnmsyOv9", "known_device_token": "eYbOdF7bfI9fZrjuqiavCMxV69ZuYxSSoByfBGp9", "attribution_event": "login"},
{"user": {"id": 1737925671232634880, "id_str": "1737925671232634880", "name": "Latrice Franklin", "screen_name": "LatriceFra45957"}, "next_link": {"link_type": "subtask", "link_id": "next_link", "subtask_id": "SuccessExit"}, "oauth_token": "1737925671232634880-m6DNs4dhyR6gvZcpSjv4CFMUKCYhtT", "oauth_token_secret": "uPKjAigTmhhKhd7XYQxePVS2qtVmKGMmTbhk6QENlo9pD", "known_device_token": "dgQsvYp3Az772QyGmlYPgFeFZj4l6H7ukea0ApO5", "attribution_event": "login"},
{"user": {"id": 1737900560408543232, "id_str": "1737900560408543232", "name": "Kristen Hood", "screen_name": "KristenHoo62564"}, "next_link": {"link_type": "subtask", "link_id": "next_link", "subtask_id": "SuccessExit"}, "oauth_token": "1737900560408543232-zfuVqWyjCECqeBvJtoObe9pwtutoF9", "oauth_token_secret": "alaSpI7WPFPrOJuJ2JZfL9m8RQpHEYnc1Hjuzt9PZeJ3p", "known_device_token": "IgyucN0akduI89Iiy1rPp3XvgrSo215pZgSmgTdx", "attribution_event": "login"},
{"user": {"id": 1737917143315021824, "id_str": "1737917143315021824", "name": "Elizabeth Wells", "screen_name": "ElizabethW69120"}, "next_link": {"link_type": "subtask", "link_id": "next_link", "subtask_id": "SuccessExit"}, "oauth_token": "1737917143315021824-1nsfywG7BFKqME2v4IO6h8C1GWOQC0", "oauth_token_secret": "UpZEHk2Rv0claQKnBtVVy8blOAGYK8DnwRmPo60J6scfF", "known_device_token": "rdNqSPQOPEivtORHsYxVsIaSORr01UL875tv8r8e", "attribution_event": "login"},
{"user": {"id": 1737917360416112640, "id_str": "1737917360416112640", "name": "Melinda Martin", "screen_name": "MelindaM53095"}, "next_link": {"link_type": "subtask", "link_id": "next_link", "subtask_id": "SuccessExit"}, "oauth_token": "1737917360416112640-uqEWsQ5SOBcMnz6LFfklkHvu83flaR", "oauth_token_secret": "a8VWftjl97Lyn2wlymjw1Q6TV3MXrQptpAc9TQQkHk9w9", "known_device_token": "EQSFnE0HnbNtfjBN9woYrOCQvkssElrFor65rTWU", "attribution_event": "login"},
{"user": {"id": 1737917343857082368, "id_str": "1737917343857082368", "name": "Sarah Lester", "screen_name": "SLester59992"}, "next_link": {"link_type": "subtask", "link_id": "next_link", "subtask_id": "SuccessExit"}, "oauth_token": "1737917343857082368-g4MVQGlXW9Ctc4C3049XwZHxxAiPzm", "oauth_token_secret": "OSQqmMjRhbp521JyYAruLACHU9mQJsJPNXYvTFUZNu7Fu", "known_device_token": "ImL6pR1ki8z2eUOJNwSsAACTNuufVABDpEZVKBDw", "attribution_event": "login"},
{"user": {"id": 1737918047208296449, "id_str": "1737918047208296449", "name": "Tammy Lewis", "screen_name": "TammyLewis11012"}, "next_link": {"link_type": "subtask", "link_id": "next_link", "subtask_id": "SuccessExit"}, "oauth_token": "1737918047208296449-xeNtUIGUUTkDV6jsN44fEdqqZJcleQ", "oauth_token_secret": "k7CnszTau42MkcQZJH8YTU1FWmyu1eCLsWsQ4CChV3DNU", "known_device_token": "SVUa3ywTWmQvid0QPnE4l0O1N1fw0pXZAuW6n8MI", "attribution_event": "login"},
{"user": {"id": 1737917911056936960, "id_str": "1737917911056936960", "name": "Julie Zhang", "screen_name": "JulieZhang89672"}, "next_link": {"link_type": "subtask", "link_id": "next_link", "subtask_id": "SuccessExit"}, "oauth_token": "1737917911056936960-aK3PASr7SHnTUmBdPhCb6O9KPbiPHp", "oauth_token_secret": "CDlHkbMbvMCQq7wYB2G7aJvNNRQgVZrZfqw0LlRXdWWcc", "known_device_token": "c6Nec9b2YUCJn67pSnbIRGmxR6M03AGZs8fJEivB", "attribution_event": "login"},
{"user": {"id": 1737917199975624704, "id_str": "1737917199975624704", "name": "Crystal Lawrence", "screen_name": "CrystalLaw69121"}, "next_link": {"link_type": "subtask", "link_id": "next_link", "subtask_id": "SuccessExit"}, "oauth_token": "1737917199975624704-uEN1PgWraiMDgvYuno9fb6EDHqsbZB", "oauth_token_secret": "hFUjxdMUWnAPo2r4c9L5ktUyWo2VnbNI26O1pqW5kbAa0", "known_device_token": "1gnsC03SbYpW7vpiersnPqyLfxtmGIuUTvF9D6Y8", "attribution_event": "login"},
{"user": {"id": 1737917319173799938, "id_str": "1737917319173799938", "name": "Patricia Monroe", "screen_name": "MonroePatr42022"}, "next_link": {"link_type": "subtask", "link_id": "next_link", "subtask_id": "SuccessExit"}, "oauth_token": "1737917319173799938-ph8haUfn5Zkz4NdEFHQ2hzDc8BGIqv", "oauth_token_secret": "GmRmXILTH5Ae3ijf0XJFhscir42n9bkMkZFDJwMnijPHU", "known_device_token": "ppnzlTK5xCoUZRnuw808KRNRPs5tsDsaNHdNZn4z", "attribution_event": "login"},
{"user": {"id": 1737918296169529344, "id_str": "1737918296169529344", "name": "Wendy Hendrickson", "screen_name": "WendyHendr92113"}, "next_link": {"link_type": "subtask", "link_id": "next_link", "subtask_id": "SuccessExit"}, "oauth_token": "1737918296169529344-m7vSnKa9oW399qVmLo8SNX6AxJ0rjB", "oauth_token_secret": "be0tVHd6sFfc0R9XZlJiJHsW7T95fGFHlBsznaMgG1FQz", "known_device_token": "G30lHW2NaS4724bWVFGclhD5oUN9lKJQTxgKUFuE", "attribution_event": "login"},
{"user": {"id": 1737917054576168960, "id_str": "1737917054576168960", "name": "Mary Davis", "screen_name": "MaryDavis472395"}, "next_link": {"link_type": "subtask", "link_id": "next_link", "subtask_id": "SuccessExit"}, "oauth_token": "1737917054576168960-sXHCBoCSlGNesFCtkIKIrKEFihrGlr", "oauth_token_secret": "9vcG2ulIBXQGhdzVHxGIMdkeHjNg4LvYjwEOMgtHnJb0A", "known_device_token": "3TMtYObcPYLW6CkH1fZvi3D73p4Y4ssj3QhNSyua", "attribution_event": "login"},
{"user": {"id": 1737917023164989441, "id_str": "1737917023164989441", "name": "Nichole Smith", "screen_name": "NicholeSmi55181"}, "next_link": {"link_type": "subtask", "link_id": "next_link", "subtask_id": "SuccessExit"}, "oauth_token": "1737917023164989441-qgChoyqxH83ebxWvc68A62C20sN5Hs", "oauth_token_secret": "cySljJvgOcMPe1I8afkAOsGiTAJZIiOmgOloSt6P8BgJq", "known_device_token": "KZFWdukI3lzIvHOhxFXjeoWdWpOvc3kNm7Rla6h9", "attribution_event": "login"},
{"user": {"id": 1737924945181659136, "id_str": "1737924945181659136", "name": "Amanda Taylor", "screen_name": "AmandaTayl29537"}, "next_link": {"link_type": "subtask", "link_id": "next_link", "subtask_id": "SuccessExit"}, "oauth_token": "1737924945181659136-JmFWWqn4w6TsWl4m8zN3PFcLNKm4OX", "oauth_token_secret": "SuYjtYMWMuZCjw78bG6CYcl7x0vlTlD0U7cb1CzF0IDAo", "known_device_token": "AUBV97GIjEGLlBNXqOqQjspH4z1PlpN1bbR8UPaD", "attribution_event": "login"},
{"user": {"id": 1737923830021033985, "id_str": "1737923830021033985", "name": "Chelsea Dominguez", "screen_name": "ChelseaDom79705"}, "next_link": {"link_type": "subtask", "link_id": "next_link", "subtask_id": "SuccessExit"}, "oauth_token": "1737923830021033985-04J7SAWyAiqpwJR1lLU9NqLbMWChcd", "oauth_token_secret": "Oa7UeGXo5enwGRbPgVQOuT9H29PeOIYxb79EGgfat2dRs", "known_device_token": "SaGbF020ajyzCvxkhRPf5L9R4jtuGzHeYPqu3nJE", "attribution_event": "login"},
{"user": {"id": 1737925021807374336, "id_str": "1737925021807374336", "name": "Sarah Thompson", "screen_name": "SarahThomp40463"}, "next_link": {"link_type": "subtask", "link_id": "next_link", "subtask_id": "SuccessExit"}, "oauth_token": "1737925021807374336-zkFohYR3bTGnch4H2oUPMsvbC4pqqh", "oauth_token_secret": "wnbzSCNPejuiBJtOMYXCj8mIdO8n7x44vcrzlh5urs01h", "known_device_token": "ubhsmKrxJGXGzIgnVHJE62x8tvP3QEbGbnoAgnUU", "attribution_event": "login"},
{"user": {"id": 1737926127031590912, "id_str": "1737926127031590912", "name": "Alexis Jenkins", "screen_name": "AlexisJenk26238"}, "next_link": {"link_type": "subtask", "link_id": "next_link", "subtask_id": "SuccessExit"}, "oauth_token": "1737926127031590912-tmeY4v2gcycA6p7bxKnmWULO4RrL1c", "oauth_token_secret": "RMqghQU0qHguqg8LFeMX68fi5vGBg2iQekoo6RajyrOmD", "known_device_token": "4ZloXqiISDurfif9zQ3cD69jMRVylSZPJl7WUdos", "attribution_event": "login"},
{"user": {"id": 1737925172081098752, "id_str": "1737925172081098752", "name": "Denise Reyes", "screen_name": "DeniseReye7897"}, "next_link": {"link_type": "subtask", "link_id": "next_link", "subtask_id": "SuccessExit"}, "oauth_token": "1737925172081098752-l0ZOxEuYb5szVfrsYqZ9mbbiT9cASL", "oauth_token_secret": "5VIEmSECZiI4ysOvyicFFtNRpSqIgOxkqTWKIHwJokeow", "known_device_token": "Uv4WAw5FIOwwSlHvbMUQdGSAMeJcFbkg1MODCZgb", "attribution_event": "login"},
{"user": {"id": 1795505598349352960, "id_str": "1795505598349352960", "name": "Elise Green", "screen_name": "EliseGreen10784"}, "next_link": {"link_type": "subtask", "link_id": "next_link", "subtask_id": "SuccessExit"}, "oauth_token": "1795505598349352960-f3nO5qtXjnAAbwOfJM3V9F6888OgDQ", "oauth_token_secret": "H39sVE8Q1o0UJNdLbiXY7uLI35jXqx9t1MXgEgQTmT56Q", "known_device_token": "YfneGUEAkLz54p3oxtEG6GOroM2AjheUxEX1X5NX", "attribution_event": "login"},
{"user": {"id": 1795505224175509504, "id_str": "1795505224175509504", "name": "Shelly Hove", "screen_name": "HoveShelly52455"}, "next_link": {"link_type": "subtask", "link_id": "next_link", "subtask_id": "SuccessExit"}, "oauth_token": "1795505224175509504-JwWgbBVERRngAYZSiFNh6GM7lvy110", "oauth_token_secret": "0Q0NrqKDjQzP9dkKzkJh2EcsMgEG6Eg73BlYeEjvS6F2X", "known_device_token": "Q21YbrpLdj9aLupMHQ2MrEErgK6GzmrR58IGB26G", "attribution_event": "login"},
{"user": {"id": 1795506167747100673, "id_str": "1795506167747100673", "name": "Jennifer Wright", "screen_name": "JenniferWr83482"}, "next_link": {"link_type": "subtask", "link_id": "next_link", "subtask_id": "SuccessExit"}, "oauth_token": "1795506167747100673-CbHjVKQdcDoj5rKjiCFgyx4OEgqaPo", "oauth_token_secret": "vc5nLAbJr8qQXPnOumERrGMoByMVD4NRiew3pc72Fvg5p", "known_device_token": "ImoW1FJ4IenGY14WoE0Z3UtxOkaemEvTwOFCDaiH", "attribution_event": "login"},
{"user": {"id": 1795505118902915072, "id_str": "1795505118902915072", "name": "Katy Nasby", "screen_name": "KatyNasby92549"}, "next_link": {"link_type": "subtask", "link_id": "next_link", "subtask_id": "SuccessExit"}, "oauth_token": "1795505118902915072-dS7NugtqCRH8uLkIwynvQX4p92Z4ng", "oauth_token_secret": "ztS3Gsicg12pUBiFNSuQZwEVKNxxkOnDKEVt5Wr2odCDC", "known_device_token": "r8IkfzxvXU01kGN2RMms9097nNv5P1ojFycQT5IK", "attribution_event": "login"},
{"user": {"id": 1795505579470749696, "id_str": "1795505579470749696", "name": "Kelsey Johnson", "screen_name": "KelseyJohn73250"}, "next_link": {"link_type": "subtask", "link_id": "next_link", "subtask_id": "SuccessExit"}, "oauth_token": "1795505579470749696-d6wozVQsYFqY7pq85Tjf145aDqonlT", "oauth_token_secret": "yvfGXQvW9TxpST8qyXqlDwB29gmzJ9E5U5Z7Rdp2VLIC0", "known_device_token": "qKKskADVlcbcysZ4SgIzXcRWe5nttsRXjYGrjLii", "attribution_event": "login"},
{"user": {"id": 1795505534759583746, "id_str": "1795505534759583746", "name": "Laurie Diamond", "screen_name": "LaurieDiam86046"}, "next_link": {"link_type": "subtask", "link_id": "next_link", "subtask_id": "SuccessExit"}, "oauth_token": "1795505534759583746-V1clCFjiBQ6VwCef2CpyurWtkH7z1x", "oauth_token_secret": "IMzsRJ1KcwrfwUUEEQ94UIz3rf85qHpjDcesHFizM3dlV", "known_device_token": "dZTYopaLCRmmPnYtZ6L1Cw0L0k6hYERZIKe4HKZm", "attribution_event": "login"},
{"user": {"id": 1795506081197678592, "id_str": "1795506081197678592", "name": "Lory Shea", "screen_name": "LoryShea43652"}, "next_link": {"link_type": "subtask", "link_id": "next_link", "subtask_id": "SuccessExit"}, "oauth_token": "1795506081197678592-u80pEJQ51SRUhf4na941EegaDEF3ze", "oauth_token_secret": "BArDFTJnNvo0Zy0comCkoXDH2a8ox9iP1rFiP2nzH2u0b", "known_device_token": "tWh8XT0Ds61CuADJKqlqha2GXot9lVQb7B4bOFOG", "attribution_event": "login"},
{"user": {"id": 1795506101632294912, "id_str": "1795506101632294912", "name": "Natasha Evans", "screen_name": "NatashaEva42258"}, "next_link": {"link_type": "subtask", "link_id": "next_link", "subtask_id": "SuccessExit"}, "oauth_token": "1795506101632294912-wdfbx5XkxQh1LJLSaBHjSWoXZijpLI", "oauth_token_secret": "xzrKsHp64feKb1rej9nJzykWXFUlaM5dUcL07E4fvXiwb", "known_device_token": "MAOcVNCT1Li9xH20ASnoikTo17OygJFbAJJrATW3", "attribution_event": "login"},
{"user": {"id": 1795506184364945409, "id_str": "1795506184364945409", "name": "Shelley Schroeder", "screen_name": "ShelleySch23413"}, "next_link": {"link_type": "subtask", "link_id": "next_link", "subtask_id": "SuccessExit"}, "oauth_token": "1795506184364945409-ATMWZTBkYK918Scmu9FbI8TAzQVxX9", "oauth_token_secret": "JK6rAlVY0FVL4qya38Uqj4b8MpAiKuW2wj4RAR8DOVBlC", "known_device_token": "rhLenopyVbJs62jjJfth6SI3j0cmmyPV61aqqfwl", "attribution_event": "login"},
{"user": {"id": 432185525, "id_str": "432185525", "name": "alfio salemi", "screen_name": "AlfioSalemi"}, "next_link": {"link_type": "subtask", "link_id": "next_link", "subtask_id": "SuccessExit"}, "oauth_token": "432185525-LxFKc9PlyXf94lUuXlqixCtRecI5i28Dh36czrQy", "oauth_token_secret": "80vER4Q5PdG9tjniSJBvxGT20yThz6BYTROKc2u5ZQ6fL", "known_device_token": "sMfuUdxfzRQkU0qVFRZgdeAmGNfb0DWHY7ckgl0L", "attribution_event": "login"},
  {"user": {"id": 825575678, "id_str": "825575678", "name": "olukunle ola", "screen_name": "timolsoft"}, "next_link": {"link_type": "subtask", "link_id": "next_link", "subtask_id": "SuccessExit"}, "oauth_token": "825575678-txR1BxAgP9me0JFpHhaBwgIPef8CbLBrUPFkn4EC", "oauth_token_secret": "FBG9UBTWrT3tfZnFaUWIaTlNKssmp00zmqZ82Y43l6tUL", "known_device_token": "999yw5ZXhlYFN90ZsGhq2yJttxKRiPD8Dxc3rX3q", "attribution_event": "login"},
  {"user": {"id": 479936058, "id_str": "479936058", "name": "Kayleigh Sharkey", "screen_name": "KayleighSharkey"}, "next_link": {"link_type": "subtask", "link_id": "next_link", "subtask_id": "SuccessExit"}, "oauth_token": "479936058-yVw4yacncrNYpDAidN0ZeNWrJ1qN6y4h2VrYykLr", "oauth_token_secret": "EI3R63WXIXOolnOBQPHm5ZfRBrRlyGDFKM2ZHIO5hS7vU", "known_device_token": "F9xYK1a1jWKCbOz3ihtyARjXDtBABmJaXFOwNvfn", "attribution_event": "login"},
  {"user": {"id": 965817978, "id_str": "965817978", "name": "Antony", "screen_name": "antonyxavier505"}, "next_link": {"link_type": "subtask", "link_id": "next_link", "subtask_id": "SuccessExit"}, "oauth_token": "965817978-JLy0tGetS784hWHJMV6fSimbOQzPuUyLeix826Rs", "oauth_token_secret": "FCuEf851YFY4V9vwBqLCNcwQXSt3U2oSKF3E21keikPhY", "known_device_token": "cMrxI9yVvTkHOWXWtkMoRWzEDcVnVLTroPcsn9zV", "attribution_event": "login"},
  {"user": {"id": 2786088472, "id_str": "2786088472", "name": "kevin riemarsch", "screen_name": "KRiemarsch14"}, "next_link": {"link_type": "subtask", "link_id": "next_link", "subtask_id": "SuccessExit"}, "oauth_token": "2786088472-sD62TBA3WmDf3mBcLuvvnxGfwiNvkBofN8XlBa7", "oauth_token_secret": "MkBGrPR5a7ug0UwO6gbxtpyaemqqNT7AtJ0q4riFXLjjR", "known_device_token": "kC6NlmcZy68Ay300yuEtBjHs9GbtUJSYPDdLseef", "attribution_event": "login"},
  {"user": {"id": 1131211093, "id_str": "1131211093", "name": "WileEtanTy", "screen_name": "Wile_Ty"}, "next_link": {"link_type": "subtask", "link_id": "next_link", "subtask_id": "SuccessExit"}, "oauth_token": "1131211093-lQLlAFrO2cXipNmFdGLsZ43ZdGLUWfTpyjuIUan", "oauth_token_secret": "2OKQMzk3YljETgYUVs8uauTwruiBeSHmrQ954jZgH6iAp", "known_device_token": "sLFTdRXGMlVhA7q5wTmSs1TEhfB9gDIAcJwVUUU2", "attribution_event": "login"},
  {"user": {"id": 2234045508, "id_str": "2234045508", "name": "toni proudlock", "screen_name": "toniproudlock"}, "next_link": {"link_type": "subtask", "link_id": "next_link", "subtask_id": "SuccessExit"}, "oauth_token": "2234045508-j3mYmsJ8SDmEo9lslDDlqcxRdPn1ptckLcU0F4S", "oauth_token_secret": "UCNjpqDzjvg64KFeTkkkd6k5GPmcbIxbiC3PTSjgzkRlD", "known_device_token": "YOtzByz226FHN8dxdreAB1ur9nQquc62ITqecmUy", "attribution_event": "login"},
  {"user": {"id": 3027631594, "id_str": "3027631594", "name": "Skye Doughty", "screen_name": "SkyeDoughty"}, "next_link": {"link_type": "subtask", "link_id": "next_link", "subtask_id": "SuccessExit"}, "oauth_token": "3027631594-tATS4h4wujF9Tpnf4LuUmT4mqDm0dCefeXXSgmM", "oauth_token_secret": "R2HRXRZiOKkhTSuLfyHYKgtfXgcXs97v3tX1GspRrTsVQ", "known_device_token": "zqEIDgqYSMmfOYNWBFYywklS3CwUxheFGpyseBmf", "attribution_event": "login"},
  {"user": {"id": 387297480, "id_str": "387297480", "name": "jacek", "screen_name": "gonzales1166"}, "next_link": {"link_type": "subtask", "link_id": "next_link", "subtask_id": "SuccessExit"}, "oauth_token": "387297480-jGvNKhv0MZYHq2QN2EEOKj31fbZbHKy285r9iIiy", "oauth_token_secret": "VAaLatazmPSWgKBpG4I4vgdyNCeAoT7k2EDveBhvpddUy", "known_device_token": "Nmd53pMKIpO6R4iR0IyWg3SSgb9JOMw4K5gi65NF", "attribution_event": "login"},
  {"user": {"id": 957989730, "id_str": "957989730", "name": "Blanpain Julien", "screen_name": "witekoek"}, "next_link": {"link_type": "subtask", "link_id": "next_link", "subtask_id": "SuccessExit"}, "oauth_token": "957989730-MwkQKS0N0unxywJkT17FN3dp6AxDzWX5Oxb31CIT", "oauth_token_secret": "I3ahrux1NAYSVztvE6BGOZ06rPYLJ7ghKYacRA1dE3Trt", "known_device_token": "zX436tegk3vdZqjcbLDXTzlarneemaNkTkTCAlLZ", "attribution_event": "login"},
  {"user": {"id": 257260754, "id_str": "257260754", "name": "gleiston cardoso", "screen_name": "gleistoncardoso"}, "next_link": {"link_type": "subtask", "link_id": "next_link", "subtask_id": "SuccessExit"}, "oauth_token": "257260754-AW6yldmWHXb9zo61dSglKFOwhawqNZqgG2GSHAuW", "oauth_token_secret": "vE88NolMeaEpmDRjl4dwGm5nBcI8EGVqC5uclmTWulwt9", "known_device_token": "PPBfpjLlbtnc6gYBKyMgtg7nML1IZZKqKgSR0lLC", "attribution_event": "login"},
  {"user": {"id": 770510360, "id_str": "770510360", "name": "matthew zambrano", "screen_name": "ZambranoMatthew"}, "next_link": {"link_type": "subtask", "link_id": "next_link", "subtask_id": "SuccessExit"}, "oauth_token": "770510360-mSkx4Xirh3OuzNdGEmZGB8YvaoXcOQhHgzCQTCOY", "oauth_token_secret": "BKMsGJCiNBE4G8wkbIoSOUxtijXV4qV62DQXjjpjZY4HM", "known_device_token": "2fCsL9GG8Hn163LqViiu28WCQwA8oZlrfV3qKbKb", "attribution_event": "login"},
  {"user": {"id": 3101522989, "id_str": "3101522989", "name": "Balajithegreat", "screen_name": "balaji2376"}, "next_link": {"link_type": "subtask", "link_id": "next_link", "subtask_id": "SuccessExit"}, "oauth_token": "3101522989-zx2s1Fgvf89kt2hewHA2gZ3qAQNRlAfE9ZBNS5N", "oauth_token_secret": "NF8xKvHL6yYKtTmj8Dun7RIFKGYElugRETlWlBtbriJWx", "known_device_token": "AzAFRgvyantUUMV9yWsY2Rp2c0xeMfnw2xjN5pY2", "attribution_event": "login"},
  {"user": {"id": 414515619, "id_str": "414515619", "name": "\u674e\u4f9d\u4f9d", "screen_name": "vsop0306"}, "next_link": {"link_type": "subtask", "link_id": "next_link", "subtask_id": "SuccessExit"}, "oauth_token": "414515619-iL6l788Y9FOjpu2FhXI1Ly6VPaVtnH00ADYPeigH", "oauth_token_secret": "PxBNf4oR9o94rufhxbZH3EjfgFplbkaJhCaB8sk8QiwTr", "known_device_token": "58pPp9EVPE7neCPsxg2hK8li3z8Hh3WkHGdSMrpi", "attribution_event": "login"},
  {"user": {"id": 3704221513, "id_str": "3704221513", "name": "Nani\ua9c1IP\ua9c2", "screen_name": "manchunani1"}, "next_link": {"link_type": "subtask", "link_id": "next_link", "subtask_id": "SuccessExit"}, "oauth_token": "3704221513-JwgbDzgPCaltVSGKNbcAfwXESsvZGabS9DhRwvZ", "oauth_token_secret": "xP2A12p0bXDbOn0YWn7d3DJULEhLS943fC26u2ciq0C2w", "known_device_token": "QzfEa2Mx9vYmn0KWfaMRBV2Ci1hJbsdfpBOcRM5F", "attribution_event": "login"},
  {"user": {"id": 607927655, "id_str": "607927655", "name": "Tim Forrest", "screen_name": "timforrest69"}, "next_link": {"link_type": "subtask", "link_id": "next_link", "subtask_id": "SuccessExit"}, "oauth_token": "607927655-zgOG2dkqHn78jyjEHDkdMcBundvD6Xd4QfCGERrf", "oauth_token_secret": "itp4eRwIk2FL0E6egsGkea3MhRZ3pLTSFPxvCYgs40D6a", "known_device_token": "HNFcuy83033lifXtZQ2CuU3ByojQr55neZaImm9y", "attribution_event": "login"},
  {"user": {"id": 1691069126, "id_str": "1691069126", "name": "Zdzichu Wiertara", "screen_name": "karix9606"}, "next_link": {"link_type": "subtask", "link_id": "next_link", "subtask_id": "SuccessExit"}, "oauth_token": "1691069126-xHXK5rO698ZCixBt35iw6HKro8dQxbSpTxaTjtN", "oauth_token_secret": "MJ0zAOXyT3xlfpaoepzzKhcy8sQYjb2lwUQEbQ2jBEj4G", "known_device_token": "MmBvXphDPpyAAwX9lf5SZiy5rH4qJlE59h5S6JV2", "attribution_event": "login"},
  {"user": {"id": 542289044, "id_str": "542289044", "name": "Mathew Tooze", "screen_name": "MathewTooze"}, "next_link": {"link_type": "subtask", "link_id": "next_link", "subtask_id": "SuccessExit"}, "oauth_token": "542289044-ioS8IdXt2FBAAVNde1KdRDgCiA0gwPe1IIYgfPYu", "oauth_token_secret": "YJ0WPljUSRmcWVaFTz3FAFBUaSv3YTbxED6YoSOvQ0ujW", "known_device_token": "SSUBzhtbILpzQjAhXTZ7arENegI2kGKz4e8WB49Q", "attribution_event": "login"},
  {"user": {"id": 1413340280, "id_str": "1413340280", "name": "\u0421\u0435\u0440\u0433\u0435\u0439 \u0421\u0438\u0434\u043e\u0440\u043e\u0432", "screen_name": "ssalamander98"}, "next_link": {"link_type": "subtask", "link_id": "next_link", "subtask_id": "SuccessExit"}, "oauth_token": "1413340280-iyk0XmaeGjhnxP3TJj2UjlncPyjSkP0WrUSWdiL", "oauth_token_secret": "jRwGQi34MfqQCqU7tCHjf0HDe8WYwfzSDIfrNZuUUndkl", "known_device_token": "Uflf6herY5tMXlnvn80sIUGNqxkZoniA8HmaPuvH", "attribution_event": "login"},
  {"user": {"id": 528706491, "id_str": "528706491", "name": "nicole smelley", "screen_name": "NicoleSmelley"}, "next_link": {"link_type": "subtask", "link_id": "next_link", "subtask_id": "SuccessExit"}, "oauth_token": "528706491-JBSuhkmaNzXYXjauKtGcFzIliomrmeIyNdHVa7OQ", "oauth_token_secret": "Vb6yTg3vJkztMz6A7IDRcWMjN2C9hRYw6geKwipwY13Y7", "known_device_token": "2ptahSFZX9TtzyvnJkpsyDpYktfDV7TbJb09RIJJ", "attribution_event": "login"},
  {"user": {"id": 3018603323, "id_str": "3018603323", "name": "Joe Lewis", "screen_name": "jlew1058"}, "next_link": {"link_type": "subtask", "link_id": "next_link", "subtask_id": "SuccessExit"}, "oauth_token": "3018603323-viR8L1e3wVShcFA7zBHD0bn1vn5nePAVq84bdrt", "oauth_token_secret": "mIAYy9UFfvu34o0KcR99eCDoEBMBou2nPadewCqpYJyI0", "known_device_token": "rruMjh4cnACy7ibo6h7cgeMgNDjcYCSlvOsIcgyo", "attribution_event": "login"},
  {"user": {"id": 596286444, "id_str": "596286444", "name": "Manan", "screen_name": "MananDhanani"}, "next_link": {"link_type": "subtask", "link_id": "next_link", "subtask_id": "SuccessExit"}, "oauth_token": "596286444-Hvxa5FVjO7Pqf1WbdfdRFqVviPUMpKqqcu8lAOYY", "oauth_token_secret": "lwIMdozOE0GOLDzOGAd5SOvo0LiIFpw8jkXWT6qUCVntJ", "known_device_token": "7WHmSOqXr6uXXLBecXcWxXnp4xMFVKrVXZBLIDuu", "attribution_event": "login"},
  {"user": {"id": 186316793, "id_str": "186316793", "name": "ryan gavin", "screen_name": "rggavin1"}, "next_link": {"link_type": "subtask", "link_id": "next_link", "subtask_id": "SuccessExit"}, "oauth_token": "186316793-dJ5oT7CZ9GEWb1T652Ny7jLpBtSoLYzK4oLbjDwK", "oauth_token_secret": "pMMGtqZV77VlEpove1G4RMMKSQng3K5vPeTNRBLAQYX4W", "known_device_token": "ytIQvOPHTmZgXNsBtwVRQMUN9yQsrVdkJROLad0s", "attribution_event": "login"},
  {"user": {"id": 483927437, "id_str": "483927437", "name": "Richard charles", "screen_name": "Charlescago"}, "next_link": {"link_type": "subtask", "link_id": "next_link", "subtask_id": "SuccessExit"}, "oauth_token": "483927437-pZV3RYvdiwbGJPxXVHcB9JifwmeKGNxuhpgsNxWf", "oauth_token_secret": "y2rA4XbOzr35T58Y8FZcJBaLZNgmMKsDlxaNHttfmypTa", "known_device_token": "CqEmVlF3LMUWww2eT7qVU2Hdy4QFFX02yFVfWVp3", "attribution_event": "login"},
  {"user": {"id": 396205855, "id_str": "396205855", "name": "simon stenger", "screen_name": "SimonStenger"}, "next_link": {"link_type": "subtask", "link_id": "next_link", "subtask_id": "SuccessExit"}, "oauth_token": "396205855-FwMnuYZyduscK40pKy9kxSxsck2Wre1FG2TEwcE1", "oauth_token_secret": "l6G9ywIkjwaTvmzuV2jQeGAp72PX6GQnWEFc5urc2OBk7", "known_device_token": "93SonpZyIYAlB0nrbo83ri7xiX92M4C0NPZz6NBV", "attribution_event": "login"},
  {"user": {"id": 2927244678, "id_str": "2927244678", "name": "sintodandu", "screen_name": "sintodandu"}, "next_link": {"link_type": "subtask", "link_id": "next_link", "subtask_id": "SuccessExit"}, "oauth_token": "2927244678-DACYfsSKbkzThCkpzqo6bIzhGF40tf4HzK4EyNQ", "oauth_token_secret": "ZN2ZJyF3EHVMlTvLGiODQMlZR6BMHmBJvZwk5htlKlY4W", "known_device_token": "f00jXNpUSnBk5akrQRHUYGmtLRTkpdyBDBDaKr3u", "attribution_event": "login"},
  {"user": {"id": 813040195, "id_str": "813040195", "name": "Henrik Ingvarsson", "screen_name": "ingven555"}, "next_link": {"link_type": "subtask", "link_id": "next_link", "subtask_id": "SuccessExit"}, "oauth_token": "813040195-V2zMpfLhShI9mroXv3GwAzdqq26FVRu7WZH3U2gU", "oauth_token_secret": "jZsQfF9zyOJGCwXj73iouOJntdbtwPsnJYch9WGxEGwMg", "known_device_token": "jK12VdaPeV71ezLXabSMBQEbJUBSS9IDa8t5uXye", "attribution_event": "login"},
  {"user": {"id": 2979458986, "id_str": "2979458986", "name": "zaida dughman", "screen_name": "ZaidaDughman"}, "next_link": {"link_type": "subtask", "link_id": "next_link", "subtask_id": "SuccessExit"}, "oauth_token": "2979458986-kv995qsH4TkzSOWItL9dThdFSdhi61YwLyJErQ4", "oauth_token_secret": "6be9itHts61xGIyNwxz8551ZyR9uIGzMzMqI7tteb2jOX", "known_device_token": "METEdlI0GAOeRVLzivnrhN9UjPZEXuCAlNn7RLUN", "attribution_event": "login"},
  {"user": {"id": 2859527362, "id_str": "2859527362", "name": "Scott McKnight", "screen_name": "Scott_1602"}, "next_link": {"link_type": "subtask", "link_id": "next_link", "subtask_id": "SuccessExit"}, "oauth_token": "2859527362-MSsgskHGvwMpDmCs03UNP7lnP9Tpbbt7QP9V6D1", "oauth_token_secret": "q6LoJhYa6yG9fkg40PHMRDjJ5dhmvg8w5Y8O5WlNtVNEn", "known_device_token": "blX2ARbvsLaKV09mKnPQLzdyDllSrGx891Mv5K8f", "attribution_event": "login"},
  {"user": {"id": 396813825, "id_str": "396813825", "name": "ahmet aky\u00fcz", "screen_name": "hausak61"}, "next_link": {"link_type": "subtask", "link_id": "next_link", "subtask_id": "SuccessExit"}, "oauth_token": "396813825-YJjaQSfjs0yKnL3wEQn1WhJEnJAVcHZK5EigSGcX", "oauth_token_secret": "U3e480d9KrcALlPUh7D1s2dg6hDYbnqYiEme8D1Pyhblk", "known_device_token": "DzIKtY1Yd0Po9JAbKtbiY7PdwSgn4ib8LCcYwOva", "attribution_event": "login"},
  {"user": {"id": 404108108, "id_str": "404108108", "name": "Magdalena \u017bu\u0142awa\ud83e\udde1 Ordzaar", "screen_name": "majazolw"}, "next_link": {"link_type": "subtask", "link_id": "next_link", "subtask_id": "SuccessExit"}, "oauth_token": "404108108-XSfBr7C9MW3bicOuTXW3egXhV24phocjTZ3k4NxM", "oauth_token_secret": "MFtpmRIACDPVM65iCfSBsJCzzTY0BTX6OAaoHSUaQXuub", "known_device_token": "EvUZwxLOkqgFtghVYtqzCzJM332iuB8hehvhDOiq", "attribution_event": "login"},
  {"user": {"id": 891769867, "id_str": "891769867", "name": "doniselees", "screen_name": "doniselees"}, "next_link": {"link_type": "subtask", "link_id": "next_link", "subtask_id": "SuccessExit"}, "oauth_token": "891769867-vOkHngWnN9DItjUm89P03yJzPtPyJh3sInhNafac", "oauth_token_secret": "sPWoBCTn0UYjP2XHe6aYG6APCADymkVU34CcErDNfViJf", "known_device_token": "beK20AEnPk8wnB8r0lnsMWZlZmJ0UV6Zxr2D73ye", "attribution_event": "login"},
  {"user": {"id": 845285886, "id_str": "845285886", "name": "Mark Murray", "screen_name": "Deadcell656"}, "next_link": {"link_type": "subtask", "link_id": "next_link", "subtask_id": "SuccessExit"}, "oauth_token": "845285886-UjaMUBspLRTjU658XUmeuWRkhz29wlSc9YiprSjE", "oauth_token_secret": "3H3whYkwlN0dGxIXQUm1QE8D4ZLhEAYpRvcS8Mlfk2RhV", "known_device_token": "KVrJaj1olqsz18Tkz3uNa4wfTAWV6e8PH0vaQkjM", "attribution_event": "login"},
  {"user": {"id": 1199924144, "id_str": "1199924144", "name": "tesfahun getaneh", "screen_name": "tesfahungm"}, "next_link": {"link_type": "subtask", "link_id": "next_link", "subtask_id": "SuccessExit"}, "oauth_token": "1199924144-ZxIKNX3IfcwWPi3YM1IWyLf0tK7z87k9AnNa1Aj", "oauth_token_secret": "oe7YngnENZhRpHlx2rLhUOicvCFhy2INSma5eHObSL9X9", "known_device_token": "ozblEBciyXMGfXY5tKuL2IO7fkdAHSJf37JoLH0b", "attribution_event": "login"},
  {"user": {"id": 735616634, "id_str": "735616634", "name": "\u0639\u0628\u062f\u0627\u0644\u0631\u062d\u0645\u0646", "screen_name": "wayed7r"}, "next_link": {"link_type": "subtask", "link_id": "next_link", "subtask_id": "SuccessExit"}, "oauth_token": "735616634-G2L0gnxpBCab7aAiEXOatv4f8mU56qCh8kKAkHsm", "oauth_token_secret": "ISrxdy6WaJWGKoXIsCrgWyn6yWZxqGFisdFbEq3ywYVW0", "known_device_token": "4gF68CdXMNio5lIdWPKLkPVT5LYOIcGP7JofqC3C", "attribution_event": "login"},
  {"user": {"id": 287104496, "id_str": "287104496", "name": "Janji29", "screen_name": "janji_29"}, "next_link": {"link_type": "subtask", "link_id": "next_link", "subtask_id": "SuccessExit"}, "oauth_token": "287104496-tNhK3HqBbJ8aQPFk3w3d2FqnfQLUBkComeP48b5P", "oauth_token_secret": "PIciHzlCsQcWQdZHvjB7NthUuGGbskHvaYbowxTfmnr0a", "known_device_token": "qdY1qm2PxYyWw23im53AmTRIDjSzMHNz90yGBe7y", "attribution_event": "login"},
  {"user": {"id": 2314280675, "id_str": "2314280675", "name": "Sara dasilva", "screen_name": "loolswag"}, "next_link": {"link_type": "subtask", "link_id": "next_link", "subtask_id": "SuccessExit"}, "oauth_token": "2314280675-78i01iqA4cbbDbfZCPWPy8Lzpw96ww0keMTcNru", "oauth_token_secret": "ycb7GMUz0mnz7XewjDM0NUDctPXUdmxQ8BQRLgrewcXoH", "known_device_token": "j3dDDB4wyXF3v1HVevpWAGuwWYkY4ths3BaNuWfk", "attribution_event": "login"},
  {"user": {"id": 714280312, "id_str": "714280312", "name": "Staceygesese", "screen_name": "Staceygesese"}, "next_link": {"link_type": "subtask", "link_id": "next_link", "subtask_id": "SuccessExit"}, "oauth_token": "714280312-DPrcTjZvr9tOCOC1dUSQ1nUA8Utdzj6WFkcOJfjW", "oauth_token_secret": "wxtl9IUjPWwPgIeCCgNOG1psS2T68QfO2kIFQF7CMMAHZ", "known_device_token": "NaFKIyoPn9VT42HGv0gzwzD9uA0SCcr6eGPviyN6", "attribution_event": "login"},
  {"user": {"id": 2617444292, "id_str": "2617444292", "name": "Mateusz Zubek", "screen_name": "lanuys13"}, "next_link": {"link_type": "subtask", "link_id": "next_link", "subtask_id": "SuccessExit"}, "oauth_token": "2617444292-Ro6jhKYQ3ZB128hQrolEuzujs7ugEwJFqNYy63y", "oauth_token_secret": "5u8WQ9MtHcjfG21ZIlDegv1eL2snlEmfqupZxU2Ds2fjG", "known_device_token": "zJ7nw3gmNtugIDVYF86jOlMwfTnfVz8eiNUftocX", "attribution_event": "login"},
  {"user": {"id": 885747541, "id_str": "885747541", "name": "Michelle Pierfax", "screen_name": "MichellePierfax"}, "next_link": {"link_type": "subtask", "link_id": "next_link", "subtask_id": "SuccessExit"}, "oauth_token": "885747541-ImF5AVo9wrkAtLUtxHn3wI8w12OYOpI6iCy8EALB", "oauth_token_secret": "iPJBJgLYoUcQNyCjgWhW0aESrQmabT1kfs5W5hi79n1iQ", "known_device_token": "D68rRk26HXuLlkfTHXAwcstrYmaCKsJNLA16AXVY", "attribution_event": "login"},
  {"user": {"id": 721072682, "id_str": "721072682", "name": "Nya", "screen_name": "najita38"}, "next_link": {"link_type": "subtask", "link_id": "next_link", "subtask_id": "SuccessExit"}, "oauth_token": "721072682-nIxXgufMi7Alwki3INTBR0KPNmBub7v8DfvNxJ4B", "oauth_token_secret": "lpIpjDNZisQuxuer7qlTp8Vpk5fLCqymOCm5OIxwoX3qL", "known_device_token": "yKCaBS32ijWvv0p4n4qBqIWogmYgsxyd20ZzdnU0", "attribution_event": "login"},
  {"user": {"id": 576360415, "id_str": "576360415", "name": "katia", "screen_name": "katialabriola"}, "next_link": {"link_type": "subtask", "link_id": "next_link", "subtask_id": "SuccessExit"}, "oauth_token": "576360415-knVlrObJtfKAGdGPYoPqKoupGlvn9PIlYX6NXyZF", "oauth_token_secret": "FjbZuUmKtc4w3NgxDD8KajRAojmERw7wysHVLQqllWAQu", "known_device_token": "8iW2QbubFPQrubnhQggWhHXzwjsR9zsQhUFPmC0E", "attribution_event": "login"},
  {"user": {"id": 3148823973, "id_str": "3148823973", "name": "Ala Kr\u00f3liczek ", "screen_name": "ala_kroliczek"}, "next_link": {"link_type": "subtask", "link_id": "next_link", "subtask_id": "SuccessExit"}, "oauth_token": "3148823973-gbURo4VpTJ3RZLj7tdNUBOTqbAz1UXmcdcFtDsy", "oauth_token_secret": "dxoaWTIOid0vBsRD0RjYNZfaYVQSqj89QGRWoHv9f7UXL", "known_device_token": "i6aMA1YCTbCXymJx3FbpA6cn4LOIGQ2Q9SJUGHQK", "attribution_event": "login"},
  {"user": {"id": 1096816735, "id_str": "1096816735", "name": "mike smith", "screen_name": "lovenduski56"}, "next_link": {"link_type": "subtask", "link_id": "next_link", "subtask_id": "SuccessExit"}, "oauth_token": "1096816735-u4tPvlHZsbFQFWe25s1qZkkEVcBh775BWBZmzUZ", "oauth_token_secret": "2DsWT3tsTwaxTFrxsQFqi9DTttByL6SYkI5hww3jduRzB", "known_device_token": "8BDAJolX03gCLXqxRA934NvdExG2SgBBSbqZGh5W", "attribution_event": "login"},
  {"user": {"id": 2429355322, "id_str": "2429355322", "name": "joe perian", "screen_name": "jcperian"}, "next_link": {"link_type": "subtask", "link_id": "next_link", "subtask_id": "SuccessExit"}, "oauth_token": "2429355322-JH9X3VNANn24S7ftNF3GGnUkcyfmBFPy9szt9fz", "oauth_token_secret": "IWgd6UHnLF1sNifTuVxcYqmi5FhIfujcS2dl3FdvnCtGe", "known_device_token": "ujAhE1CDuufLOZC51RNJVZIAbSEyqVnNxHBadEh1", "attribution_event": "login"},
  {"user": {"id": 349530224, "id_str": "349530224", "name": "Marcus Taylor", "screen_name": "Mtayl86"}, "next_link": {"link_type": "subtask", "link_id": "next_link", "subtask_id": "SuccessExit"}, "oauth_token": "349530224-bD072L3bOVSbAjaNJqxgGte5fPxk7pEUNESbyiqS", "oauth_token_secret": "Aev00hrh6RQkhEcJc0sB3XYKWZx0QpeeLwgEoNpJmpQqF", "known_device_token": "JL3MPGSMdeZTuqq7XyAWRqgLZiEEPPLFTRplBVw6", "attribution_event": "login"},
  {"user": {"id": 441775480, "id_str": "441775480", "name": "Marco Leone", "screen_name": "MarcoLeone94"}, "next_link": {"link_type": "subtask", "link_id": "next_link", "subtask_id": "SuccessExit"}, "oauth_token": "441775480-SNKQsGS4FRiLuoQUPAkoDM47oPdPfEnpbM5lQj7z", "oauth_token_secret": "TRWHJiCv2SF2rkJtyXE8LmMvYOTmuJ1aKIlUiQTjb7UO5", "known_device_token": "NJhFiyebMSSKGoCAq0XmzD6J4AEEDssGWOtvCBBx", "attribution_event": "login"},
  {"user": {"id": 2226971726, "id_str": "2226971726", "name": "luana hellen bezerra", "screen_name": "luanahellen31"}, "next_link": {"link_type": "subtask", "link_id": "next_link", "subtask_id": "SuccessExit"}, "oauth_token": "2226971726-Z0BBaCjDmE9iU4C43X0MrzJWU1BWylWoCADp4mx", "oauth_token_secret": "UL5R5pjDCwa1tbhROVjncuC7UIKWAuImFa0xVqHzjwsyS", "known_device_token": "ZaKEpY5gp28MFklG56nh2DYW1V2kg3CKCDhFSUaU", "attribution_event": "login"},
  {"user": {"id": 1531951058, "id_str": "1531951058", "name": "Destinie", "screen_name": "destf69"}, "next_link": {"link_type": "subtask", "link_id": "next_link", "subtask_id": "SuccessExit"}, "oauth_token": "1531951058-7YQkm8W5ZKOB11P2aPi4JPk0NKL1LNRhljRbBsx", "oauth_token_secret": "oaj1F0CxpJudLZOd06EKPt7dbJMfpFclx8ZCZOEXq3nXV", "known_device_token": "vzlPMXeOeUQEw53YR0V8NPLAjOzpeZbmsG62vSpr", "attribution_event": "login"},
  {"user": {"id": 236728091, "id_str": "236728091", "name": "Lori Cline", "screen_name": "lorilanell67"}, "next_link": {"link_type": "subtask", "link_id": "next_link", "subtask_id": "SuccessExit"}, "oauth_token": "236728091-YwDnP0HSDmzYzUlzTXQZkecJNkTYoVLX5hJb348L", "oauth_token_secret": "YixTiRUDY7biwpFSKc76DiUkSqhOLCej6U6aG6MQcU4Wa", "known_device_token": "JTD2fb1TpoWGZiCHckcP8xrGi9exel5F4cx0vgzi", "attribution_event": "login"},
{"user": {"id": 305260090, "id_str": "305260090", "name": "Rocio Bel\u00e9n", "screen_name": "RebolledoRocio"}, "next_link": {"link_type": "subtask", "link_id": "next_link", "subtask_id": "SuccessExit"}, "oauth_token": "305260090-gxkDdZ5yg4f0tBC1cvd2wnvBcHIPuVDpqOz0Nl4c", "oauth_token_secret": "9irf5F4LA5hW1AWV8i7nlDsYtW8KPLWLEHaTbKZdCa0wR", "known_device_token": "tWJNpI2HKU6kUh7OtlrhzloX7vBbfHleUfcU2ocm", "attribution_event": "login"},
  {"user": {"id": 568071142, "id_str": "568071142", "name": "Brandon Schieweck", "screen_name": "BSchieweck"}, "next_link": {"link_type": "subtask", "link_id": "next_link", "subtask_id": "SuccessExit"}, "oauth_token": "568071142-7iO5P2pQer9JX9UZOhXM9bSRTFbLhp70qpgMSH68", "oauth_token_secret": "R2ZDSogsFJ7rN9Wmp9eyhWDtzE4BvwQJRYzYRLbCZq2T3", "known_device_token": "jQtme36CvWg20g6VU7zanZ4nhFEH3wzM4PAqwXep", "attribution_event": "login"},
  {"user": {"id": 72722751, "id_str": "72722751", "name": "M. Saif Gonz\u00e1lez", "screen_name": "martesaif"}, "next_link": {"link_type": "subtask", "link_id": "next_link", "subtask_id": "SuccessExit"}, "oauth_token": "72722751-OrOP9p0DbFAyLh0Z2XlzfZaueMANe3ghoeZhUo6sk", "oauth_token_secret": "kEYTj5fPHjU5X0AbsLF0n15XyHvjHmAilB3tAH67hbvhV", "known_device_token": "8OQeeq05Odxvnut1ZpogWxrcNxeFpmyxAQ4mbu51", "attribution_event": "login"},
  {"user": {"id": 934540903422857216, "id_str": "934540903422857216", "name": "Lisa Hilliard", "screen_name": "ScareWea"}, "next_link": {"link_type": "subtask", "link_id": "next_link", "subtask_id": "SuccessExit"}, "oauth_token": "934540903422857216-EcXznwFopJNIRY63q78DlcNDNLwwkvg", "oauth_token_secret": "wHcn96R6pVT0EgXOp8zZa0goxpxGdcKlClDb2KnBxquOB", "known_device_token": "Z8vadrLNFMwRW55xmgH8EyOstrTXgmkDMZ9uX98P", "attribution_event": "login"},
  {"user": {"id": 2434439972, "id_str": "2434439972", "name": "moroniah osuna", "screen_name": "moroniahosuna"}, "next_link": {"link_type": "subtask", "link_id": "next_link", "subtask_id": "SuccessExit"}, "oauth_token": "2434439972-RKtQTPNE2zmCgfHnsaoFVWSsMD9mkD6XTsJammX", "oauth_token_secret": "tljsoISBOwZnlqtT3aghwSB1rXJ1YTVbBjQGloQ2xmwgM", "known_device_token": "zUWsrAvRLOJVdpgRK6iwFZ1cCJBAom3FgPnHEuqf", "attribution_event": "login"},
  {"user": {"id": 315771211, "id_str": "315771211", "name": "Sasori", "screen_name": "ZhezzMezz"}, "next_link": {"link_type": "subtask", "link_id": "next_link", "subtask_id": "SuccessExit"}, "oauth_token": "315771211-NzJfRX4zczimVFVWV5grk0A2TrHHsIIE2oxqKyhG", "oauth_token_secret": "NQ4zngfcrKOfwUdcnSct0hBqgLwq7Z8aggwuTbSU2oOEK", "known_device_token": "UjkqtikD41esG7QXTW3kBl2J3V1pmQtz4W4Hpv2O", "attribution_event": "login"},
  {"user": {"id": 226873660, "id_str": "226873660", "name": "jovan mitic", "screen_name": "jovan035"}, "next_link": {"link_type": "subtask", "link_id": "next_link", "subtask_id": "SuccessExit"}, "oauth_token": "226873660-wNHIGI0FRfmwE6A3ulYDySkb7kdKq3JDwkDTorzG", "oauth_token_secret": "NGPx4io3lhwdXzJbJAwK3qtos0KXsgpohFO8to8d9YyVs", "known_device_token": "GiuDrlCSOL0ahXjJSKWhkrISJhmlkCL1Q4EoCVZd", "attribution_event": "login"},
  {"user": {"id": 87734695, "id_str": "87734695", "name": "seb\ua9c1IP\ua9c2", "screen_name": "barny17"}, "next_link": {"link_type": "subtask", "link_id": "next_link", "subtask_id": "SuccessExit"}, "oauth_token": "87734695-p2i9r08Cuub1vRFwzv5qKm7wC5XRjgj6E39rJKGGr", "oauth_token_secret": "zc0o6lcfnrGQxe4b4o7et7Z1rqgyfT2wrVPaWRSA90Igx", "known_device_token": "MvsEBfpVwcv5GQNs8garlzObFbMwIl60XYWpAVMi", "attribution_event": "login"},
  {"user": {"id": 1887504078, "id_str": "1887504078", "name": "jeni", "screen_name": "memsjenny"}, "next_link": {"link_type": "subtask", "link_id": "next_link", "subtask_id": "SuccessExit"}, "oauth_token": "1887504078-OffWw6buTn9Lmfm8gXEA60acju88v1LbVJvVXCo", "oauth_token_secret": "K1SfPpPdovoygIVnMLhdhHq8BjYUxivSgSywxsy1ajn55", "known_device_token": "8S0rvvqGNeaRbSqGWtCLu1x8BqXLLs4l1csngUtL", "attribution_event": "login"},
  {"user": {"id": 3036655217, "id_str": "3036655217", "name": "Rude Oblivion", "screen_name": "RudeOblivion"}, "next_link": {"link_type": "subtask", "link_id": "next_link", "subtask_id": "SuccessExit"}, "oauth_token": "3036655217-8NgC5vh3fZRdLiEYl29PecbrQbPntAUc63wVlNc", "oauth_token_secret": "WP2QE9C91ByuFHjhX5oJxWpq3XAaLA6DHrpepA2fBer5H", "known_device_token": "Euuntk7kKnFhEiUx6uTMvBPPclyU0IG8tnztZo4N", "attribution_event": "login"},
  {"user": {"id": 761704231, "id_str": "761704231", "name": "Simone graham", "screen_name": "Simone_Graham"}, "next_link": {"link_type": "subtask", "link_id": "next_link", "subtask_id": "SuccessExit"}, "oauth_token": "761704231-TQfKQLUH2exct7SVtVgzMxjkjcWL1w1fXKys7A2J", "oauth_token_secret": "eKj82OsQbX4MAf5qGJiCWUi2ypdykliqxTHWsu2RsEfwE", "known_device_token": "23jHiEhAJooUHUZKJgw8VmUhU8hK9BEVd6tvWgNu", "attribution_event": "login"},
  {"user": {"id": 1119363920, "id_str": "1119363920", "name": "Maria Moore", "screen_name": "fenmoore1"}, "next_link": {"link_type": "subtask", "link_id": "next_link", "subtask_id": "SuccessExit"}, "oauth_token": "1119363920-ccgsvnbxSwJy8rOEEDggGRLcnVMS14GYULwxVIj", "oauth_token_secret": "3X4iS7WBRMnukS5BYkwVTU4vXx3jugfHfjFQuxSmrpt5x", "known_device_token": "bhPufZbkkDS0GzbeITAtx8qSZYYkF64bauzpqB2r", "attribution_event": "login"},
  {"user": {"id": 333978325, "id_str": "333978325", "name": "Vaggelis Poultour", "screen_name": "poultour_gr"}, "next_link": {"link_type": "subtask", "link_id": "next_link", "subtask_id": "SuccessExit"}, "oauth_token": "333978325-bLZzAF5lJxIUYy1oLogayOSdDgOuhA1R0ESsl3yT", "oauth_token_secret": "Sc6BV9EDCziptBmumbK80PJF6wd5OdFzPHS5L8IgzOK5z", "known_device_token": "zBDMIcpVmOB8btsNN0CKAzkC2FjMC4hsXnzr0N8m", "attribution_event": "login"},
  {"user": {"id": 525201701, "id_str": "525201701", "name": "april cadua", "screen_name": "devil_hotshot"}, "next_link": {"link_type": "subtask", "link_id": "next_link", "subtask_id": "SuccessExit"}, "oauth_token": "525201701-TL6QNgb2xsMlQjMJZ2mVSFPzO5v1wcWVoV5mepsl", "oauth_token_secret": "Ux1KdPgHgIRDHgCQYiCeCck6EtWTWYin2fPvOc9lKEtkX", "known_device_token": "KtdYpnFifvuiH3LUMH13Fz2lSomzMavaAOeE2tRs", "attribution_event": "login"},
  {"user": {"id": 2328272578, "id_str": "2328272578", "name": "luca", "screen_name": "luca1052"}, "next_link": {"link_type": "subtask", "link_id": "next_link", "subtask_id": "SuccessExit"}, "oauth_token": "2328272578-imDd2GBQ2TdP7dd8f49eRv9TXD1mEkP5fqkAKfN", "oauth_token_secret": "uM55zuHmhWAvJbDYDNv3SMybS61AsNuXgTFWHneHQATGL", "known_device_token": "hV4CI45Hoz6mAbUmYfWiyjI5xkCLB3NwwD4mVZ2k", "attribution_event": "login"},
  {"user": {"id": 288332647, "id_str": "288332647", "name": "Majory Paula", "screen_name": "MajoryPaula"}, "next_link": {"link_type": "subtask", "link_id": "next_link", "subtask_id": "SuccessExit"}, "oauth_token": "288332647-dfxvrOiub8g5edJhZHSlkw3xK0DGX1Zd6TpFMMOw", "oauth_token_secret": "GotBPcClVP8mPoHQTd5fDnz31MXeMB9AkPAYmsXPQVaIt", "known_device_token": "vODKohU1JCE2V0GrE91cSY6bP1OeyxRgZDkxxuFg", "attribution_event": "login"},
  {"user": {"id": 933299756, "id_str": "933299756", "name": "Ashley Jowett", "screen_name": "ashjow86"}, "next_link": {"link_type": "subtask", "link_id": "next_link", "subtask_id": "SuccessExit"}, "oauth_token": "933299756-B7AMpLM2Qam5aufyZfe8L8vel3ZFPeIASIXZx82v", "oauth_token_secret": "jV2wlEPS8rsPP6wlLJXVRhX0NOMWnqaxQMdWwIoPAhRm8", "known_device_token": "mMF7HBO44slu2F8UtFgNNx0TfyXux3bmgkFXq5E9", "attribution_event": "login"},
  {"user": {"id": 1648436197, "id_str": "1648436197", "name": "m_almutairi", "screen_name": "m3ath_almutairi"}, "next_link": {"link_type": "subtask", "link_id": "next_link", "subtask_id": "SuccessExit"}, "oauth_token": "1648436197-CWNAPlGRNL55B8VwAOJ8ICU9U278Jh3NpKGHllU", "oauth_token_secret": "vKx4sO4jNRx3Jz1ADltNW5ZtuA2dcuwG0TJ7S8oJ4NnHO", "known_device_token": "7C9Zjb8zRaxPqISHlr9tIvcje4HiaOS1EZ34YIHx", "attribution_event": "login"},
  {"user": {"id": 857964800, "id_str": "857964800", "name": "zolile pakade|Ultiverse\u26a1\ufe0f\ud83d\udc11", "screen_name": "zolilepakade"}, "next_link": {"link_type": "subtask", "link_id": "next_link", "subtask_id": "SuccessExit"}, "oauth_token": "857964800-MsrAs8Xs7plJUhV5RU728ndGvRhcDJmKrSR5sCqV", "oauth_token_secret": "Y4HGkfu3O86V3xJRXxaFzwQ4aCIHYZiyfJALqck0YoP5T", "known_device_token": "p3yWUVKNWpuX6OUJmSvmLYSuOv5zJJVaKiZbS4AX", "attribution_event": "login"},
  {"user": {"id": 234117396, "id_str": "234117396", "name": "Ana Ravenne", "screen_name": "ana_ravenne"}, "next_link": {"link_type": "subtask", "link_id": "next_link", "subtask_id": "SuccessExit"}, "oauth_token": "234117396-dcrjoOcqlRSNsf1FnLqHPOeqd4tOfbZTQhmcxdWG", "oauth_token_secret": "qRTtXhY2Ga1lZ035Ziis7BQIMQX3LY1xFmerQPC5GLbjX", "known_device_token": "B0URHBRz0C9injvQdYUGeOpUdkjnTNnbJ4f5xzIh", "attribution_event": "login"},
  {"user": {"id": 3397175391, "id_str": "3397175391", "name": "Carlos daniel villar", "screen_name": "carlitomiusic45"}, "next_link": {"link_type": "subtask", "link_id": "next_link", "subtask_id": "SuccessExit"}, "oauth_token": "3397175391-GKkEzxTD6P9b2qIW1xZi9eNaktkHsjDTZWJGNL2", "oauth_token_secret": "IsLh5wVjsjxZai2wMxampKYgEi0ErciiIvOp0rMyR5uDZ", "known_device_token": "2QcHT11qbKxbUHqDTct1WviTe2vS01abJpxa3tvr", "attribution_event": "login"},
  {"user": {"id": 1935031092, "id_str": "1935031092", "name": "Mayara Carvalho", "screen_name": "mayarinhasvm"}, "next_link": {"link_type": "subtask", "link_id": "next_link", "subtask_id": "SuccessExit"}, "oauth_token": "1935031092-S1XzPozuJnAxCfF6twBJudAGHxHNeNHMpMd7x5i", "oauth_token_secret": "XMUdWHQ0kgHl3HimZ4fH3YYzBP2yYAyjalT8clVOa8V0Z", "known_device_token": "7XsubyWIGLGEt5m2FWiSXuL2Q2Y72gb1fjpH8xdG", "attribution_event": "login"},
  {"user": {"id": 268119815, "id_str": "268119815", "name": "Roberta Vasconcelos", "screen_name": "betinha_vs"}, "next_link": {"link_type": "subtask", "link_id": "next_link", "subtask_id": "SuccessExit"}, "oauth_token": "268119815-I6qnE56NKcS2BjjabqV1UbVaEJfYlko0hnFx3mos", "oauth_token_secret": "BZ5WvMey63s4ahIODfuEr16iTkEosGzH50TiYECkwneM6", "known_device_token": "wjzzQO0pYgHto0wiu92PnY0jfWK5TnqroV23mymo", "attribution_event": "login"},
  {"user": {"id": 2730277576, "id_str": "2730277576", "name": "NurhierwegenYoutu", "screen_name": "janakettenstock"}, "next_link": {"link_type": "subtask", "link_id": "next_link", "subtask_id": "SuccessExit"}, "oauth_token": "2730277576-zPSyQtDP4YcJg37ULU1E80wNgRfsiT1p3vTvvxL", "oauth_token_secret": "7syFa85E00KxuSftIRNq9ZG83glTZ3bM7DbGRh2ht50bJ", "known_device_token": "PAhgzVTtrtpanRoCOf6znSkuaDHgogJsJKTnzPjU", "attribution_event": "login"},
  {"user": {"id": 2249993491, "id_str": "2249993491", "name": "Jessica", "screen_name": "op_chieh"}, "next_link": {"link_type": "subtask", "link_id": "next_link", "subtask_id": "SuccessExit"}, "oauth_token": "2249993491-E3Y3RtUhQqxaTF1SNzTTPDjwA5K9ZmoD7Zq1ecL", "oauth_token_secret": "kwMkfdMxZ8wPfjMhxE0X0L03L3Xb91TObqN1S6gbucFvX", "known_device_token": "eKnc3RMmfXQMDGhZCAXltJT0fDx5UdH1MpgHu5S1", "attribution_event": "login"},
  {"user": {"id": 186241198, "id_str": "186241198", "name": "Jordan Elizondo", "screen_name": "JE_Turtlez"}, "next_link": {"link_type": "subtask", "link_id": "next_link", "subtask_id": "SuccessExit"}, "oauth_token": "186241198-ok2HeeSwWb8Q7SwWrGj1fqfjMBs5XEr3DC8Wp9om", "oauth_token_secret": "hzDEAqPtQEzX38y4TPNryJHQJu7hIHghI0oB1Rh0H2qdh", "known_device_token": "GYktnjl3cqe7hAW6vj6tYzsd0Azsi2YsqQR1waEO", "attribution_event": "login"},
  {"user": {"id": 376642387, "id_str": "376642387", "name": "ADELEKE BABATUNDE", "screen_name": "tunde_folks"}, "next_link": {"link_type": "subtask", "link_id": "next_link", "subtask_id": "SuccessExit"}, "oauth_token": "376642387-BClOhx4pZTfV01UJdHURc6zPVZCfVDW6qXBtGGIP", "oauth_token_secret": "J7WosFDKOQng0dKf4fLWKgL5ScFbm7FGzGOHiPgWch1YE", "known_device_token": "ct5YI1xPG2HuedqtR9YDHxxxdfVTpvCI3HjnUFvi", "attribution_event": "login"},
  {"user": {"id": 2459074851, "id_str": "2459074851", "name": "Emir G\u00fczel", "screen_name": "bemirguzel41"}, "next_link": {"link_type": "subtask", "link_id": "next_link", "subtask_id": "SuccessExit"}, "oauth_token": "2459074851-UPULH106jAHkQx7TwCS0eN0NVGLM9REPZmnFYyc", "oauth_token_secret": "KLILmd4I6jjVg4U8dn8Fib4F5Plr2sKZN8SVcB2zxudLm", "known_device_token": "fBF1eweMa95ShAq2rhIY9vpjdkE2DmEKCLVps6q7", "attribution_event": "login"},
  {"user": {"id": 3076136494, "id_str": "3076136494", "name": "EH j ah DG GN VB", "screen_name": "lemansero"}, "next_link": {"link_type": "subtask", "link_id": "next_link", "subtask_id": "SuccessExit"}, "oauth_token": "3076136494-TqlMLUngRZVpmrehhXzHySsCb4yrC1dKAtjYaFz", "oauth_token_secret": "0rEjxRkUql75xXND7qxXPQ21aV3BU1ZiHkv85JMUJGc9b", "known_device_token": "A6jXytHRWLO6m30P2kCKbZZekFvO7CkJg6KJQ4Eb", "attribution_event": "login"},
  {"user": {"id": 284654551, "id_str": "284654551", "name": "Leonid", "screen_name": "Leonname"}, "next_link": {"link_type": "subtask", "link_id": "next_link", "subtask_id": "SuccessExit"}, "oauth_token": "284654551-EWJiKNgZuTFElK3qguPSs8NHbKIer3ZjmvfH37U9", "oauth_token_secret": "N17ppu3UZwAzHLAlE6kZThPQnNbg2V0c0MG8FPmDhgzEn", "known_device_token": "V8Q6oussecMPdNV6MlV1QiicQLFZWh81FSCkbVeL", "attribution_event": "login"}]